codesight/__init__.py
codesight/cli.py
codesight/config.py
codesight/core.py
codesight/exclusions.py
codesight/formatter.py
codesight/run.py
codesight/terminal.py
codesight/templates/analyzer.py
codesight/templates/config.template.json
codesight-0.1.4.dist-info/METADATA
codesight-0.1.4.dist-info/WHEEL
codesight-0.1.4.dist-info/entry_points.txt
codesight-0.1.4.dist-info/RECORD
