Metadata-Version: 2.4
Name: codesight
Version: 0.1.4
Summary: CodeSight - Code analysis and visualization tool
Project-URL: Homepage, https://github.com/mattsilv/codesight
Project-URL: Issues, https://github.com/mattsilv/codesight/issues
Author-email: Matt Silverman <mattsilverman@example.com>
License: MIT
Requires-Python: >=3.8
Requires-Dist: click>=8.1.3
Requires-Dist: pandas>=2.0.3
Requires-Dist: requests>=2.28.0
Requires-Dist: rich>=13.4.0
Requires-Dist: tiktoken>=0.5.0
Provides-Extra: dev
Requires-Dist: black>=23.0.0; extra == 'dev'
Requires-Dist: pre-commit>=3.3.2; extra == 'dev'
Requires-Dist: pytest>=7.0.0; extra == 'dev'
